agentsilex/__init__.py
agentsilex/agent.py
agentsilex/agent_as_tool.py
agentsilex/callbacks.py
agentsilex/extract_function_schema.py
agentsilex/function_tool.py
agentsilex/mcp.py
agentsilex/observability.py
agentsilex/run_result.py
agentsilex/runner.py
agentsilex/session.py
agentsilex/stream_event.py
agentsilex/tool.py
agentsilex/utils.py
agentsilex-0.9.dist-info/METADATA
agentsilex-0.9.dist-info/WHEEL
agentsilex-0.9.dist-info/licenses/LICENSE
agentsilex-0.9.dist-info/RECORD
