Metadata-Version: 2.4
Name: agentsilex
Version: 0.9
Summary: A transparent, minimal, and hackable agent framework
Project-URL: Homepage, https://github.com/howl-anderson/agentsilex
Project-URL: Repository, https://github.com/howl-anderson/agentsilex
Project-URL: Issues, https://github.com/howl-anderson/agentsilex/issues
Author-email: Xiaoquan Kong <u1mail2me@gmail.com>
License:                                  Apache License
License-File: LICENSE
Keywords: agent,ai,framework,litellm,llm
Classifier: Development Status :: 3 - Alpha
Classifier: Intended Audience :: Developers
Classifier: License :: OSI Approved :: MIT License
Classifier: Programming Language :: Python :: 3
Classifier: Programming Language :: Python :: 3.12
Requires-Python: >=3.12
Requires-Dist: docstring-parser>=0.17.0
Requires-Dist: litellm>=1.76.2
Requires-Dist: mcp>=1.19.0
Requires-Dist: opentelemetry-distro>=0.59b0
Requires-Dist: opentelemetry-exporter-otlp>=1.38.0
Requires-Dist: pydantic>=2.11.7
